argonauts/__init__.py
argonauts/decorators.py
argonauts/inputs.py
argonauts-0.1.2.dist-info/LICENSE
argonauts-0.1.2.dist-info/METADATA
argonauts-0.1.2.dist-info/WHEEL
argonauts-0.1.2.dist-info/RECORD
