Metadata-Version: 2.1
Name: argonauts
Version: 0.1.2
Summary: Easily convert function to interactive command line applications
License: MIT
Author: Chandra Irugalbandara
Requires-Python: >=3.10,<4.0
Classifier: License :: OSI Approved :: MIT License
Classifier: Programming Language :: Python :: 3
Classifier: Programming Language :: Python :: 3.10
Classifier: Programming Language :: Python :: 3.11
Classifier: Programming Language :: Python :: 3.12
Requires-Dist: questionary (>=2.0.1,<3.0.0)
Requires-Dist: rich (>=13.7.1,<14.0.0)
